logging_http_client/__init__.py
logging_http_client/http_headers.py
logging_http_client/http_log_record.py
logging_http_client/http_session.py
logging_http_client/logging_default_hooks.py
logging_http_client/logging_http_client_class.py
logging_http_client/logging_http_client_config.py
logging_http_client/logging_http_client_config_globals.py
logging_http_client-2.32.3.9.dist-info/LICENSE
logging_http_client-2.32.3.9.dist-info/METADATA
logging_http_client-2.32.3.9.dist-info/WHEEL
logging_http_client-2.32.3.9.dist-info/RECORD
