Metadata-Version: 2.1
Name: logging-http-client
Version: 2.32.3.9
Summary: A logging library built on top of the requests library to provide a familiar interface for sending HTTP requests with observability features out-of-the-box.
Home-page: https://github.com/u-ways/logging-http-client
License: MIT
Keywords: logging,http,client,requests
Author: u-ways
Author-email: work@u-ways.info
Requires-Python: >=3.12,<4.0
Classifier: License :: OSI Approved :: MIT License
Classifier: Operating System :: OS Independent
Classifier: Programming Language :: Python :: 3
Classifier: Programming Language :: Python :: 3.12
Classifier: Topic :: Software Development
Classifier: Topic :: Software Development :: Libraries
Classifier: Topic :: System :: Logging
Classifier: Typing :: Typed
Requires-Dist: requests (>=2.32.3,<3.0.0)
Project-URL: Documentation, https://github.com/u-ways/logging-http-client/blob/main/README.md
Project-URL: Repository, https://github.com/u-ways/logging-http-client
